brainreg_segment/__init__.py
brainreg_segment/napari.yaml
brainreg_segment/paths.py
brainreg_segment/segment.py
brainreg_segment/atlas/__init__.py
brainreg_segment/atlas/utils.py
brainreg_segment/image/__init__.py
brainreg_segment/image/utils.py
brainreg_segment/layout/__init__.py
brainreg_segment/layout/gui_constants.py
brainreg_segment/layout/gui_elements.py
brainreg_segment/layout/utils.py
brainreg_segment/regions/IO.py
brainreg_segment/regions/__init__.py
brainreg_segment/regions/analysis.py
brainreg_segment/regions/layers.py
brainreg_segment/segmentation_panels/__init__.py
brainreg_segment/segmentation_panels/regions.py
brainreg_segment/segmentation_panels/tracks.py
brainreg_segment/tracks/IO.py
brainreg_segment/tracks/__init__.py
brainreg_segment/tracks/analysis.py
brainreg_segment/tracks/fit.py
brainreg_segment/tracks/layers.py
brainreg_segment-0.2.20.dist-info/LICENSE
brainreg_segment-0.2.20.dist-info/METADATA
brainreg_segment-0.2.20.dist-info/WHEEL
brainreg_segment-0.2.20.dist-info/entry_points.txt
brainreg_segment-0.2.20.dist-info/top_level.txt
brainreg_segment-0.2.20.dist-info/RECORD
