Metadata-Version: 2.1
Name: brainreg-segment
Version: 0.2.20
Summary: Manual segmentation of 3D brain structures in a common anatomical space
Author-email: "Adam Tyson, Horst Obenhaus" <code@adamltyson.com>
License: BSD-3-Clause
Project-URL: Homepage, https://brainglobe.info/
Project-URL: Source Code, https://github.com/brainglobe/brainreg-segment
Project-URL: Bug Tracker, https://github.com/brainglobe/brainreg-segment/issues
Project-URL: Documentation, https://docs.brainglobe.info/brainreg-segment
Project-URL: User Support, https://forum.image.sc/tag/brainglobe
Classifier: Development Status :: 4 - Beta
Classifier: Intended Audience :: Developers
Classifier: Intended Audience :: Science/Research
Classifier: Operating System :: Microsoft :: Windows :: Windows 10
Classifier: Operating System :: POSIX :: Linux
Classifier: Programming Language :: Python
Classifier: Programming Language :: Python :: 3.8
Classifier: Programming Language :: Python :: 3.9
Classifier: Programming Language :: Python :: 3.10
Requires-Python: >=3.9
License-File: LICENSE
Requires-Dist: brainglobe-napari-io >=0.3.0
Requires-Dist: dask >=2.15.0
Requires-Dist: imio
Requires-Dist: brainglobe-utils >=0.2.7
Requires-Dist: napari-plugin-engine >=0.1.4
Requires-Dist: napari >=0.4.5
Requires-Dist: numpy
Requires-Dist: pandas
Requires-Dist: scikit-image
Requires-Dist: tables
Provides-Extra: dev
Requires-Dist: black ; extra == 'dev'
Requires-Dist: gitpython ; extra == 'dev'
Requires-Dist: pre-commit ; extra == 'dev'
Requires-Dist: pytest ; extra == 'dev'
Requires-Dist: coverage ; extra == 'dev'
Requires-Dist: pytest-cov ; extra == 'dev'
Requires-Dist: pytest-qt ; extra == 'dev'
Requires-Dist: napari-time-slicer ; extra == 'dev'
